orion/algo/asha.py
orion/algo/base.py
orion/algo/evolution_es.py
orion/algo/gridsearch.py
orion/algo/hyperband.py
orion/algo/mutate_functions.py
orion/algo/parallel_strategy.py
orion/algo/random.py
orion/algo/space.py
orion/algo/tpe.py
orion/algo/pbt/exploit.py
orion/algo/pbt/explore.py
orion/algo/pbt/pbt.py
orion/analysis/__init__.py
orion/analysis/base.py
orion/analysis/lpi_utils.py
orion/analysis/partial_dependency_utils.py
orion/analysis/regret_utils.py
orion/benchmark/__init__.py
orion/benchmark/benchmark_client.py
orion/benchmark/assessment/__init__.py
orion/benchmark/assessment/averagerank.py
orion/benchmark/assessment/averageresult.py
orion/benchmark/assessment/base.py
orion/benchmark/task/__init__.py
orion/benchmark/task/base.py
orion/benchmark/task/branin.py
orion/benchmark/task/carromtable.py
orion/benchmark/task/eggholder.py
orion/benchmark/task/rosenbrock.py
orion/client/__init__.py
orion/client/cli.py
orion/client/experiment.py
orion/client/manual.py
orion/client/runner.py
orion/core/__init__.py
orion/core/_version.py
orion/core/cli/__init__.py
orion/core/cli/base.py
orion/core/cli/db_main.py
orion/core/cli/evc.py
orion/core/cli/hunt.py
orion/core/cli/info.py
orion/core/cli/init_only.py
orion/core/cli/insert.py
orion/core/cli/list.py
orion/core/cli/plot.py
orion/core/cli/serve.py
orion/core/cli/status.py
orion/core/cli/checks/creation.py
orion/core/cli/checks/operations.py
orion/core/cli/checks/presence.py
orion/core/cli/db/__init__.py
orion/core/cli/db/release.py
orion/core/cli/db/rm.py
orion/core/cli/db/set.py
orion/core/cli/db/setup.py
orion/core/cli/db/test.py
orion/core/cli/db/upgrade.py
orion/core/evc/__init__.py
orion/core/evc/adapters.py
orion/core/evc/conflicts.py
orion/core/evc/experiment.py
orion/core/io/__init__.py
orion/core/io/cmdline_parser.py
orion/core/io/config.py
orion/core/io/convert.py
orion/core/io/experiment_branch_builder.py
orion/core/io/experiment_builder.py
orion/core/io/orion_cmdline_parser.py
orion-0.2.3.dist-info/LICENSE
orion-0.2.3.dist-info/METADATA
orion-0.2.3.dist-info/WHEEL
orion-0.2.3.dist-info/entry_points.txt
orion-0.2.3.dist-info/top_level.txt
orion-0.2.3.dist-info/RECORD
