Metadata-Version: 2.1
Name: orion
Version: 0.2.3
Summary: Asynchronous [black-box] Optimization
Home-page: https://github.com/epistimio/orion
Author: Epistímio
Author-email: xavier.bouthillier@umontreal.ca
License: BSD-3-Clause
Keywords: Machine Learning,Deep Learning,Distributed,Optimization
Platform: Linux
Classifier: Development Status :: 1 - Planning
Classifier: Intended Audience :: Developers
Classifier: Intended Audience :: Education
Classifier: Intended Audience :: Science/Research
Classifier: License :: OSI Approved :: BSD License
Classifier: Operating System :: POSIX
Classifier: Operating System :: Unix
Classifier: Programming Language :: Python
Classifier: Topic :: Scientific/Engineering
Classifier: Topic :: Scientific/Engineering :: Artificial Intelligence
Classifier: Programming Language :: Python :: 3
Classifier: Programming Language :: Python :: 3.6
Classifier: Programming Language :: Python :: 3.7
Classifier: Programming Language :: Python :: 3.8
Classifier: Programming Language :: Python :: 3.9
License-File: LICENSE
Requires-Dist: cloudpickle
Requires-Dist: dataclasses
Requires-Dist: PyYAML
Requires-Dist: pymongo (>=3)
Requires-Dist: numpy
Requires-Dist: scipy
Requires-Dist: gitpython
Requires-Dist: filelock
Requires-Dist: tabulate
Requires-Dist: AppDirs
Requires-Dist: plotly
Requires-Dist: kaleido
Requires-Dist: requests
Requires-Dist: pandas
Requires-Dist: gunicorn
Requires-Dist: falcon
Requires-Dist: falcon-cors
Requires-Dist: scikit-learn
Requires-Dist: psutil
Requires-Dist: joblib
Requires-Dist: pytest (>=3.0.0)
Provides-Extra: dask
Requires-Dist: dask[complete] ; extra == 'dask'
Provides-Extra: test
Requires-Dist: pytest (>=3.0.0) ; extra == 'test'
Requires-Dist: scikit-learn ; extra == 'test'
Requires-Dist: ptera (>=1.1.0) ; extra == 'test'
